<?xml version="1.0" encoding="utf-8"?>
<LanguageData>
	<MayorTitle>alcalde</MayorTitle>

  <!-- Lord job reports -->
  <LordReportAttendingElection>Visitando el lugar de votación</LordReportAttendingElection>
  <LordReportVisitingMayor>Asistiendo a la elección</LordReportVisitingMayor>
  <LordReportHangingOut>Pasando el rato con alguien</LordReportHangingOut>
  <LordReportDate>En una cita</LordReportDate>
  <LordReportAttendingFuneral>Asistiendo a funeral</LordReportAttendingFuneral>

  <!-- Miscellaneous thought log text -->
  <ConversationStage>conversación acerca de</ConversationStage>
  <ConversationEnd>[INITIATOR_nameDef] terminó una conversación con [RECIPIENT_nameDef].</ConversationEnd>
  <ConversationEnded>terminó conversación</ConversationEnded>
  <Complained>[INITIATOR_nameDef] se quejó al alcalde, [RECIPIENT_nameDef].</Complained>
  <Supported>[INITIATOR_nameDef] expresó [INITIATOR_possessive] apoyo al alcalde, [RECIPIENT_nameDef].</Supported>
  <HadMeeting>Tuvo una reunión con un constituyente</HadMeeting>

  <!-- Node descriptions -->
  <PsycheNot>No</PsycheNot>
  <PsycheSlightly>Ligeramente</PsycheSlightly>
  <PsycheLess>Menos</PsycheLess>
  <PsycheMore>Más</PsycheMore>
  <PsycheVery>Mucho</PsycheVery>
  <PsycheExtremely>Extremadamente</PsycheExtremely>
  <ConversationTooltip>People will talk about {0} to discuss this with each other.</ConversationTooltip>
	
	<!-- Comp text -->
	<CommandOfficeTableToggleLabel>Oficina del alcalde</CommandOfficeTableToggleLabel>
	<CommandOfficeTableToggleDescActive>Esta habitación está designada como la oficina de su alcalde. Si tienes un alcalde, celebrarán reuniones aquí.</CommandOfficeTableToggleDescActive>
	<CommandOfficeTableToggleDescInactive>Puedes asignar esta sala para ser utilizada como la oficina de su alcalde, si tiene uno. Puede darle a su alcalde una sola oficina.</CommandOfficeTableToggleDescInactive>

</LanguageData>