<?xml version="1.0" encoding="utf-8" ?>
<LanguageData>

<!-- Lord job reports -->
	<LordReportAttendingElection>Lieu de scrutin</LordReportAttendingElection>
	<LordReportVisitingMayor>Assister à la réunion</LordReportVisitingMayor>
	<LordReportHangingOut>Sortir avec quelqu'un</LordReportHangingOut>
	<LordReportDate>À une date</LordReportDate>

<!-- Miscellaneous thought text -->
	<ConversationStage>Conversation sur</ConversationStage>
	<ConversationEnd>Terminé une conversation avec</ConversationEnd>
	<ConversationEnded>conversation terminée</ConversationEnded>
	<Complained>Se plaint au maire.</Complained>
	<Supported>J'ai exprimé mon soutien au maire.</Supported>
	<HadMeeting>A eu une réunion avec un</HadMeeting>
	
<!-- Node descriptions -->
	<PsycheNot>Ne pas</PsycheNot>
	<PsycheSlightly>Un peu</PsycheSlightly>
	<PsycheLess>Moins</PsycheLess>
	<PsycheMore>Plus</PsycheMore>
	<PsycheVery>Très</PsycheVery>
	<PsycheExtremely>Hautement</PsycheExtremely>
	
<!-- Comp text -->
	<CommandOfficeTableToggleLabel>Mayoral office</CommandOfficeTableToggleLabel>
	<CommandOfficeTableToggleDescActive>This room is designated as your mayor's office. If you have a mayor, they will hold meetings here.</CommandOfficeTableToggleDescActive>
	<CommandOfficeTableToggleDescInactive>You can assign this room to be used as your mayor's office, if you have one. You can only give your mayor one office.</CommandOfficeTableToggleDescInactive>

</LanguageData>